ruff2bitbucket/__init__.py
ruff2bitbucket/__main__.py
ruff2bitbucket/bitbucket.py
ruff2bitbucket/capturer.py
ruff2bitbucket/common.py
ruff2bitbucket/credentials.py
ruff2bitbucket/git.py
ruff2bitbucket-0.3.0.data/scripts/ruff2bitbucket
ruff2bitbucket-0.3.0.dist-info/METADATA
ruff2bitbucket-0.3.0.dist-info/WHEEL
ruff2bitbucket-0.3.0.dist-info/entry_points.txt
ruff2bitbucket-0.3.0.dist-info/RECORD
