Metadata-Version: 2.1
Name: ruff2bitbucket
Version: 0.3.0
Summary: Send your ruff results to bitbucket as annotations.
Home-page: https://github.com/svaningelgem/ruff2bitbucket
License: MIT
Author: Steven 'KaReL' Van Ingelgem
Author-email: steven@vaningelgem.be
Requires-Python: >=3.7,<4.0
Classifier: License :: OSI Approved :: MIT License
Classifier: Programming Language :: Python :: 3
Classifier: Programming Language :: Python :: 3.7
Classifier: Programming Language :: Python :: 3.8
Classifier: Programming Language :: Python :: 3.9
Classifier: Programming Language :: Python :: 3.10
Classifier: Programming Language :: Python :: 3.11
Classifier: Programming Language :: Python :: 3.12
Requires-Dist: importlib-metadata ; python_version < "3.8"
Requires-Dist: requests
Requires-Dist: ruff
Project-URL: Repository, https://github.com/svaningelgem/ruff2bitbucket
